get_file_urls/__init__.py
get_file_urls/get_file_urls_handlre.py
uploadio_get_file_urls-1.0.1.dist-info/LICENSE
uploadio_get_file_urls-1.0.1.dist-info/METADATA
uploadio_get_file_urls-1.0.1.dist-info/WHEEL
uploadio_get_file_urls-1.0.1.dist-info/top_level.txt
uploadio_get_file_urls-1.0.1.dist-info/RECORD
