Metadata-Version: 2.1
Name: uploadio-get-file-urls
Version: 1.0.1
Summary: get file urls by id
Home-page: https://github.com/pypa/sampleproject
Author: soreka
Author-email: rezafm1001@gmail.com
License: UNKNOWN
Project-URL: Bug Tracker, https://github.com/pypa/sampleproject/issues
Platform: UNKNOWN
Classifier: Programming Language :: Python :: 3
Classifier: License :: OSI Approved :: MIT License
Classifier: Operating System :: OS Independent
Requires-Python: >=3.6
License-File: LICENSE
Requires-Dist: requests
Requires-Dist: pydantic
